odoo/addons/fleet_vehicle_service_activity/README.rst
odoo/addons/fleet_vehicle_service_activity/__init__.py
odoo/addons/fleet_vehicle_service_activity/__manifest__.py
odoo/addons/fleet_vehicle_service_activity/data/fleet_data.xml
odoo/addons/fleet_vehicle_service_activity/data/mail_data.xml
odoo/addons/fleet_vehicle_service_activity/i18n/es.po
odoo/addons/fleet_vehicle_service_activity/i18n/fleet_vehicle_service_activity.pot
odoo/addons/fleet_vehicle_service_activity/i18n/it.po
odoo/addons/fleet_vehicle_service_activity/i18n/pt_BR.po
odoo/addons/fleet_vehicle_service_activity/models/__init__.py
odoo/addons/fleet_vehicle_service_activity/models/fleet_vehicle_log_services.py
odoo/addons/fleet_vehicle_service_activity/models/res_config_settings.py
odoo/addons/fleet_vehicle_service_activity/readme/CONTRIBUTORS.md
odoo/addons/fleet_vehicle_service_activity/readme/DESCRIPTION.md
odoo/addons/fleet_vehicle_service_activity/static/description/icon.png
odoo/addons/fleet_vehicle_service_activity/static/description/index.html
odoo/addons/fleet_vehicle_service_activity/tests/__init__.py
odoo/addons/fleet_vehicle_service_activity/tests/test_vehicle_service_activity.py
odoo/addons/fleet_vehicle_service_activity/views/res_config_settings_views.xml
odoo_addon_fleet_vehicle_service_activity-18.0.1.0.0.4.dist-info/METADATA
odoo_addon_fleet_vehicle_service_activity-18.0.1.0.0.4.dist-info/WHEEL
odoo_addon_fleet_vehicle_service_activity-18.0.1.0.0.4.dist-info/top_level.txt
odoo_addon_fleet_vehicle_service_activity-18.0.1.0.0.4.dist-info/RECORD
