Metadata-Version: 2.1
Name: odoo-addon-fleet_vehicle_service_activity
Version: 18.0.1.0.0.4
Requires-Python: >=3.10
Requires-Dist: odoo==18.0.*
Summary: Activity alerts for fleet services
Home-page: https://github.com/OCA/fleet
License: AGPL-3
Author: Tecnativa, Odoo Community Association (OCA)
Author-email: support@odoo-community.org
Classifier: Programming Language :: Python
Classifier: Framework :: Odoo
Classifier: Framework :: Odoo :: 18.0
Classifier: License :: OSI Approved :: GNU Affero General Public License v3
Classifier: Development Status :: 5 - Production/Stable
